[
	{
		"chara": "",
		"bg": "",
		"bgY": 0,
		"charaX": 0,
		"charaY": 0,
		"voice": "",
		"name": "",
		"message1": "明日、隕石が墜落します。\n今すぐにシェルターに避難してください。",
		"command": 0
	},
	{
		"chara": "res/Talkart/Lyine/L_surprised.png",
		"bg": "",
		"bgY": 0,
		"charaX": 172,
		"charaY": 500,
		"voice": "res/sound/voice/L_9.wav",
		"name": "",
		"message1": "大変・・・はやく出口に向かわなきゃ！",
		"command": 1
	},
	{
		"chara": "res/Talkart/Lyine/L_surprised.png",
		"bg": "",
		"bgY": 0,
		"charaX": 172,
		"charaY": 500,
		"voice": "",
		"name": "",
		"message1": "ロジー博士、サポートをお願いします！",
		"command": 1
	},
	{
		"chara": "res/Talkart/Rlogy/R_normalarm.png",
		"bg": "",
		"bgY": 0,
		"charaX": 1400,
		"charaY": 484,
		"voice": "res/sound/voice/R_5.wav",
		"name": "",
		"message1": "任せなさい！",
		"command": 2
	},
	{
		"chara": "",
		"bg": "",
		"bgY": 0,
		"charaX": 0,
		"charaY": 0,
		"voice": "",
		"name": "",
		"message1": "",
		"command": 10
	}
]